.editorconfig
.gitignore
.gitlab-ci.yml
README.rst
publish.settings.sh
publish.sh
pyproject.toml
tsconfig.json
.idea/modules.xml
.idea/peek-core-device.iml
.idea/inspectionProfiles/Project_Default.xml
.idea/inspectionProfiles/profiles_settings.xml
peek_core_device/PlatformDependencyTest.py
peek_core_device/__init__.py
peek_core_device/plugin_package.json
peek_core_device.egg-info/PKG-INFO
peek_core_device.egg-info/SOURCES.txt
peek_core_device.egg-info/dependency_links.txt
peek_core_device.egg-info/requires.txt
peek_core_device.egg-info/top_level.txt
peek_core_device/_private/PluginNames.py
peek_core_device/_private/__init__.py
peek_core_device/_private/alembic.ini
peek_core_device/_private/admin-app/device.module.ts
peek_core_device/_private/admin-app/components/device-cache-status/device-cache-status.component.html
peek_core_device/_private/admin-app/components/device-cache-status/device-cache-status.component.scss
peek_core_device/_private/admin-app/components/device-cache-status/device-cache-status.component.ts
peek_core_device/_private/admin-app/components/device-info-table/device-info.component.html
peek_core_device/_private/admin-app/components/device-info-table/device-info.component.scss
peek_core_device/_private/admin-app/components/device-info-table/device-info.component.ts
peek_core_device/_private/admin-app/components/device-page/device-page.component.html
peek_core_device/_private/admin-app/components/device-page/device-page.component.scss
peek_core_device/_private/admin-app/components/device-page/device-page.component.ts
peek_core_device/_private/admin-app/components/device-update-table/device-update.component.html
peek_core_device/_private/admin-app/components/device-update-table/device-update.component.scss
peek_core_device/_private/admin-app/components/device-update-table/device-update.component.ts
peek_core_device/_private/admin-app/components/edit-setting-table/edit.component.html
peek_core_device/_private/admin-app/components/edit-setting-table/edit.component.scss
peek_core_device/_private/admin-app/components/edit-setting-table/edit.component.ts
peek_core_device/_private/admin-app/components/loading/loading.component.ts
peek_core_device/plugin-module/_private/hardware-info/hardware-info.ts
peek_core_device/plugin-module/_private/hardware-info/is-field.dweb.ts
peek_core_device/plugin-module/_private/hardware-info/is-field.mweb.ts
