Metadata-Version: 2.4
Name: peek-core-device
Version: 5.1.6
Summary: Peek Core Device - Device management for the peek platform
Author-email: Synerty <contact@synerty.com>
Project-URL: Homepage, https://github.com/Synerty/peek-core-device
Keywords: Peek,Python,Platform,synerty
Requires-Dist: peek-plugin-base==5.1.6
